setup.py
skim/__init__.py
skim/skim.py
skim.py.egg-info/PKG-INFO
skim.py.egg-info/SOURCES.txt
skim.py.egg-info/dependency_links.txt
skim.py.egg-info/entry_points.txt
skim.py.egg-info/top_level.txt