Metadata-Version: 1.0
Name: skim.py
Version: 0.1.1
Summary: Skim python files and display python classes and functions used
Home-page: https://github.com/mosegontar/skim.py.git
Author: Alexander Gontar
Author-email: mosegontar@gmail.com
License: MIT
Platform: UNKNOWN
